LICENSE
README.md
setup.py
nlp_pipeline/__init__.py
nlp_pipeline/files_setup.py
nlp_pipeline/nlp_pipeline.py
nlp_pipeline/search_terms.py
nlp_pipeline/text_transformation.py
nlp_pipeline/visualizations.py
nlp_pipeline.egg-info/PKG-INFO
nlp_pipeline.egg-info/SOURCES.txt
nlp_pipeline.egg-info/dependency_links.txt
nlp_pipeline.egg-info/top_level.txt
tests/__init__.py
tests/test_nlp_pipeline.py