Metadata-Version: 2.1
Name: nlp_pipeline
Version: 0.1.6
Summary: Pipelines and management structure for NLP analysis of a corpus of texts
Home-page: https://github.com/dhopp1/nlp_pipeline
Author: Daniel Hopp
Author-email: daniel.hopp1@gmail.com
Classifier: Programming Language :: Python :: 3
Classifier: License :: OSI Approved :: MIT License
Classifier: Operating System :: OS Independent
Requires-Python: >=3.6
License-File: LICENSE
